hfr/__init__.py
hfr/bb.py
hfr/category.py
hfr/message.py
hfr/topic.py
hfr_api-0.0.6.dist-info/LICENSE
hfr_api-0.0.6.dist-info/METADATA
hfr_api-0.0.6.dist-info/WHEEL
hfr_api-0.0.6.dist-info/top_level.txt
hfr_api-0.0.6.dist-info/RECORD
